{"version":"1.0","name":"Adoption Workflow","desc":"Workflow for managing the adoption process of pets in the Purrfect Pets application.","initialState":"initial_state","active":true,"states":{"initial_state":{"transitions":[{"name":"transition_to_pending","next":"PENDING","manual":false}]},"PENDING":{"transitions":[{"name":"transition_to_validated","next":"VALIDATED","manual":false,"processors":[{"name":"ValidateAdoptionProcessor","config":{"calculationNodesTags":"cyoda_application"}}]}]},"VALIDATED":{"transitions":[{"name":"transition_to_completed","next":"COMPLETED","manual":false,"processors":[{"name":"ProcessAdoptionProcessor","config":{"calculationNodesTags":"cyoda_application"}}]}]},"COMPLETED":{"transitions":[{"name":"transition_to_end","next":"final_state","manual":false}]},"final_state":{"transitions":[]}}}